{
  "parishes": [
    {
      "parish": "BUTTEVANT",
      "entries": [
        {
          "mr": "2",
          "townland": "CREGGANE",
          "os": "",
          "sublocation_1": "TOWN OF BUTTEVANT",
          "sublocation_2": "MAIN-STREET",
          "occupier": "Rev. James Cotter",
          "lessor": "Viscount Doneraile",
          "desc": "H,O,&yard,&L",
          "area": "1 2 15",
          "land_val": "3 0 0",
          "building_val": "17 0 0",
          "total_val": "20 0 0",
          "n_shared": 1,
          "is_total": 0,
          "is_exemption": 0,
          "is_continued": 1
        },
        {
          "mr": "2 a",
          "townland": "",
          "os": "",
          "sublocation_1": "",
          "sublocation_2": "",
          "occupier": "John Carroll",
          "lessor": "Rev. James Cotter",
          "desc": "H",
          "area": "",
          "land_val": "",
          "building_val": "1 10 0",
          "total_val": "1 10 0",
          "n_shared": 1,
          "is_total": 0,
          "is_exemption": 0,
          "is_continued": 0
        },
        {
          "mr": "3",
          "townland": "",
          "os": "",
          "sublocation_1": "",
          "sublocation_2": "",
          "occupier": "John Coghlan",
          "lessor": "Trustees of turnpike",
          "desc": "H",
          "area": "",
          "land_val": "",
          "building_val": "1 10 0",
          "total_val": "1 10 0",
          "n_shared": 1,
          "is_total": 0,
          "is_exemption": 0,
          "is_continued": 0
        },
        {
          "mr": "4",
          "townland": "",
          "os": "",
          "sublocation_1": "",
          "sublocation_2": "",
          "occupier": "John Coghlan",
          "lessor": "Trustees of turnpike",
          "desc": "Tolls of turnpike",
          "area": "",
          "land_val": "",
          "building_val": "",
          "total_val": "30 0 0",
          "n_shared": 1,
          "is_total": 0,
          "is_exemption": 0,
          "is_continued": 0
        },
        {
          "mr": "5",
          "townland": "",
          "os": "",
          "sublocation_1": "",
          "sublocation_2": "",
          "occupier": "",
          "lessor": "Viscount Doneraile",
          "desc": "Quarry (waste)",
          "area": "0 2 21",
          "land_val": "",
          "building_val": "",
          "total_val": "",
          "n_shared": 1,
          "is_total": 0,
          "is_exemption": 0,
          "is_continued": 0
        },
        {
          "mr": "6",
          "townland": "",
          "os": "",
          "sublocation_1": "",
          "sublocation_2": "",
          "occupier": "Ellen Weldon",
          "lessor": "Viscount Doneraile",
          "desc": "L",
          "area": "1 2 34",
          "land_val": "3 0 0",
          "building_val": "",
          "total_val": "3 0 0",
          "n_shared": 1,
          "is_total": 0,
          "is_exemption": 0,
          "is_continued": 0
        },
        {
          "mr": "7",
          "townland": "",
          "os": "",
          "sublocation_1": "",
          "sublocation_2": "",
          "occupier": "James Woods",
          "lessor": "Viscount Doneraile",
          "desc": "L",
          "area": "0 2 11",
          "land_val": "1 5 0",
          "building_val": "",
          "total_val": "1 5 0",
          "n_shared": 1,
          "is_total": 0,
          "is_exemption": 0,
          "is_continued": 0
        },
        {
          "mr": "",
          "townland": "",
          "os": "",
          "sublocation_1": "",
          "sublocation_2": "",
          "occupier": "William Daly",
          "lessor": "Viscount Doneraile",
          "desc": "H&yard",
          "area": "",
          "land_val": "",
          "building_val": "10 0 0",
          "total_val": "10 0 0",
          "n_shared": 1,
          "is_total": 0,
          "is_exemption": 0,
          "is_continued": 0
        },
        {
          "mr": "1",
          "townland": "",
          "os": "",
          "sublocation_1": "NEW-STREET",
          "sublocation_2": "",
          "occupier": "Viscount Doneraile",
          "lessor": "In fee",
          "desc": "Ball-court and garden",
          "area": "0 0 10",
          "land_val": "0 2 0",
          "building_val": "",
          "total_val": "0 2 0",
          "n_shared": 1,
          "is_total": 0,
          "is_exemption": 0,
          "is_continued": 0
        },
        {
          "mr": "2",
          "townland": "",
          "os": "",
          "sublocation_1": "",
          "sublocation_2": "",
          "occupier": "Timothy Murphy",
          "lessor": "Viscount Doneraile",
          "desc": "H,&yard,&G",
          "area": "0 0 16",
          "land_val": "0 5 0",
          "building_val": "2 0 0",
          "total_val": "2 5 0",
          "n_shared": 1,
          "is_total": 0,
          "is_exemption": 0,
          "is_continued": 0
        },
        {
          "mr": "3",
          "townland": "",
          "os": "",
          "sublocation_1": "",
          "sublocation_2": "",
          "occupier": "Patrick Murphy",
          "lessor": "Viscount Doneraile",
          "desc": "H,&yard,&G",
          "area": "0 0 14",
          "land_val": "0 4 0",
          "building_val": "1 16 0",
          "total_val": "2 0 0",
          "n_shared": 1,
          "is_total": 0,
          "is_exemption": 0,
          "is_continued": 0
        },
        {
          "mr": "4",
          "townland": "",
          "os": "",
          "sublocation_1": "",
          "sublocation_2": "",
          "occupier": "Catherine Duhig",
          "lessor": "Viscount Doneraile",
          "desc": "H,&yard,&G",
          "area": "0 0 15",
          "land_val": "0 4 0",
          "building_val": "1 1 0",
          "total_val": "1 5 0",
          "n_shared": 1,
          "is_total": 0,
          "is_exemption": 0,
          "is_continued": 0
        },
        {
          "mr": "5",
          "townland": "",
          "os": "",
          "sublocation_1": "",
          "sublocation_2": "",
          "occupier": "Edward Walsh",
          "lessor": "Viscount Doneraile",
          "desc": "H,&yard,&G",
          "area": "0 0 11",
          "land_val": "0 3 0",
          "building_val": "1 2 0",
          "total_val": "1 5 0",
          "n_shared": 1,
          "is_total": 0,
          "is_exemption": 0,
          "is_continued": 0
        },
        {
          "mr": "6",
          "townland": "",
          "os": "",
          "sublocation_1": "",
          "sublocation_2": "",
          "occupier": "Margaret Connell",
          "lessor": "Viscount Doneraile",
          "desc": "H,&yard,&G",
          "area": "0 0 13",
          "land_val": "0 3 0",
          "building_val": "0 10 0",
          "total_val": "0 13 0",
          "n_shared": 1,
          "is_total": 0,
          "is_exemption": 0,
          "is_continued": 0
        },
        {
          "mr": "7",
          "townland": "",
          "os": "",
          "sublocation_1": "",
          "sublocation_2": "",
          "occupier": "Cornelius Brian",
          "lessor": "Viscount Doneraile",
          "desc": "H,&yard,&G",
          "area": "0 0 17",
          "land_val": "0 5 0",
          "building_val": "1 15 0",
          "total_val": "2 0 0",
          "n_shared": 1,
          "is_total": 0,
          "is_exemption": 0,
          "is_continued": 0
        },
        {
          "mr": "8",
          "townland": "",
          "os": "",
          "sublocation_1": "",
          "sublocation_2": "",
          "occupier": "Eliza Lang",
          "lessor": "John Morrissey",
          "desc": "H",
          "area": "",
          "land_val": "",
          "building_val": "0 18 0",
          "total_val": "0 18 0",
          "n_shared": 1,
          "is_total": 0,
          "is_exemption": 0,
          "is_continued": 0
        },
        {
          "mr": "9",
          "townland": "",
          "os": "",
          "sublocation_1": "",
          "sublocation_2": "",
          "occupier": "John Morrissey",
          "lessor": "Viscount Doneraile",
          "desc": "H,&yard,&G",
          "area": "0 0 10",
          "land_val": "0 2 0",
          "building_val": "0 18 0",
          "total_val": "1 0 0",
          "n_shared": 1,
          "is_total": 0,
          "is_exemption": 0,
          "is_continued": 0
        },
        {
          "mr": "10",
          "townland": "",
          "os": "",
          "sublocation_1": "",
          "sublocation_2": "",
          "occupier": "John Herlihy",
          "lessor": "Ellen Weldon",
          "desc": "H,&yard,&sm. gar.",
          "area": "",
          "land_val": "",
          "building_val": "0 18 0",
          "total_val": "0 18 0",
          "n_shared": 1,
          "is_total": 0,
          "is_exemption": 0,
          "is_continued": 0
        },
        {
          "mr": "11",
          "townland": "",
          "os": "",
          "sublocation_1": "",
          "sublocation_2": "",
          "occupier": "James Crowley",
          "lessor": "Ellen Weldon",
          "desc": "H,&yard,&sm. gar.",
          "area": "",
          "land_val": "",
          "building_val": "1 0 0",
          "total_val": "1 0 0",
          "n_shared": 1,
          "is_total": 0,
          "is_exemption": 0,
          "is_continued": 0
        },
        {
          "mr": "12",
          "townland": "",
          "os": "",
          "sublocation_1": "",
          "sublocation_2": "",
          "occupier": "John Burke",
          "lessor": "Viscount Doneraile",
          "desc": "H,&yard,&sm. gar.",
          "area": "",
          "land_val": "",
          "building_val": "0 18 0",
          "total_val": "0 18 0",
          "n_shared": 1,
          "is_total": 0,
          "is_exemption": 0,
          "is_continued": 0
        },
        {
          "mr": "13",
          "townland": "",
          "os": "",
          "sublocation_1": "",
          "sublocation_2": "",
          "occupier": "Daniel Sullivan",
          "lessor": "Viscount Doneraile",
          "desc": "H,&yard,&G",
          "area": "0 0 10",
          "land_val": "0 2 0",
          "building_val": "1 2 0",
          "total_val": "1 4 0",
          "n_shared": 1,
          "is_total": 0,
          "is_exemption": 0,
          "is_continued": 0
        },
        {
          "mr": "14",
          "townland": "",
          "os": "",
          "sublocation_1": "",
          "sublocation_2": "",
          "occupier": "Viscount Doneraile",
          "lessor": "In fee",
          "desc": "Gardens",
          "area": "0 0 19",
          "land_val": "0 6 0",
          "building_val": "",
          "total_val": "0 6 0",
          "n_shared": 1,
          "is_total": 0,
          "is_exemption": 0,
          "is_continued": 0
        },
        {
          "mr": "15",
          "townland": "",
          "os": "",
          "sublocation_1": "",
          "sublocation_2": "",
          "occupier": "Edward Barrett",
          "lessor": "Cornelius Garvin",
          "desc": "H,&yard,&G",
          "area": "0 0 11",
          "land_val": "0 3 0",
          "building_val": "1 12 0",
          "total_val": "1 15 0",
          "n_shared": 1,
          "is_total": 0,
          "is_exemption": 0,
          "is_continued": 0
        },
        {
          "mr": "16",
          "townland": "",
          "os": "",
          "sublocation_1": "",
          "sublocation_2": "",
          "occupier": "Patrick Connor",
          "lessor": "Cornelius Garvin",
          "desc": "H",
          "area": "",
          "land_val": "",
          "building_val": "1 0 0",
          "total_val": "1 0 0",
          "n_shared": 1,
          "is_total": 0,
          "is_exemption": 0,
          "is_continued": 0
        },
        {
          "mr": "17",
          "townland": "",
          "os": "",
          "sublocation_1": "",
          "sublocation_2": "",
          "occupier": "Ellen Glassett",
          "lessor": "Cornelius Garvin",
          "desc": "H&small G",
          "area": "",
          "land_val": "",
          "building_val": "1 2 0",
          "total_val": "1 2 0",
          "n_shared": 1,
          "is_total": 0,
          "is_exemption": 0,
          "is_continued": 0
        },
        {
          "mr": "18",
          "townland": "",
          "os": "",
          "sublocation_1": "",
          "sublocation_2": "",
          "occupier": "John Fitzpatrick",
          "lessor": "Cornelius Garvin",
          "desc": "H,&yard,&sm. gar.",
          "area": "",
          "land_val": "",
          "building_val": "0 18 0",
          "total_val": "0 18 0",
          "n_shared": 1,
          "is_total": 0,
          "is_exemption": 0,
          "is_continued": 0
        },
        {
          "mr": "19",
          "townland": "",
          "os": "",
          "sublocation_1": "",
          "sublocation_2": "",
          "occupier": "Patrick Hickson",
          "lessor": "Cornelius Garvin",
          "desc": "H&sm. garden",
          "area": "",
          "land_val": "",
          "building_val": "0 18 0",
          "total_val": "0 18 0",
          "n_shared": 1,
          "is_total": 0,
          "is_exemption": 0,
          "is_continued": 0
        },
        {
          "mr": "20",
          "townland": "",
          "os": "",
          "sublocation_1": "",
          "sublocation_2": "",
          "occupier": "Ellen Hayes",
          "lessor": "Viscount Doneraile",
          "desc": "L",
          "area": "1 0 26",
          "land_val": "2 0 0",
          "building_val": "",
          "total_val": "2 0 0",
          "n_shared": 1,
          "is_total": 0,
          "is_exemption": 0,
          "is_continued": 0
        },
        {
          "mr": "21",
          "townland": "",
          "os": "",
          "sublocation_1": "",
          "sublocation_2": "",
          "occupier": "Margaret Sheehan",
          "lessor": "Viscount Doneraile",
          "desc": "H,&yard,&G",
          "area": "0 0 26",
          "land_val": "0 5 0",
          "building_val": "1 0 0",
          "total_val": "1 5 0",
          "n_shared": 1,
          "is_total": 0,
          "is_exemption": 0,
          "is_continued": 0
        },
        {
          "mr": "22",
          "townland": "",
          "os": "",
          "sublocation_1": "",
          "sublocation_2": "",
          "occupier": "Unoccupied",
          "lessor": "Margaret Sheehan",
          "desc": "H",
          "area": "",
          "land_val": "",
          "building_val": "0 10 0",
          "total_val": "0 10 0",
          "n_shared": 1,
          "is_total": 0,
          "is_exemption": 0,
          "is_continued": 0
        },
        {
          "mr": "23",
          "townland": "",
          "os": "",
          "sublocation_1": "",
          "sublocation_2": "",
          "occupier": "Cornelius Regan",
          "lessor": "Margaret Sheehan",
          "desc": "H",
          "area": "",
          "land_val": "",
          "building_val": "0 6 0",
          "total_val": "0 6 0",
          "n_shared": 1,
          "is_total": 0,
          "is_exemption": 0,
          "is_continued": 0
        },
        {
          "mr": "24",
          "townland": "",
          "os": "",
          "sublocation_1": "",
          "sublocation_2": "",
          "occupier": "Catherine Hallahan",
          "lessor": "Viscount Doneraile",
          "desc": "H,&yard,&G",
          "area": "0 0 21",
          "land_val": "0 5 0",
          "building_val": "1 15 0",
          "total_val": "2 0 0",
          "n_shared": 1,
          "is_total": 0,
          "is_exemption": 0,
          "is_continued": 0
        },
        {
          "mr": "25",
          "townland": "",
          "os": "",
          "sublocation_1": "",
          "sublocation_2": "",
          "occupier": "Johanna Flynn",
          "lessor": "Catherine Hallahan",
          "desc": "H",
          "area": "",
          "land_val": "",
          "building_val": "0 14 0",
          "total_val": "0 14 0",
          "n_shared": 1,
          "is_total": 0,
          "is_exemption": 0,
          "is_continued": 0
        },
        {
          "mr": "26",
          "townland": "",
          "os": "",
          "sublocation_1": "",
          "sublocation_2": "",
          "occupier": "Maurice Glassett",
          "lessor": "Timothy Murphy",
          "desc": "H,&yard,&G",
          "area": "0 0 12",
          "land_val": "0 3 0",
          "building_val": "1 5 0",
          "total_val": "1 8 0",
          "n_shared": 1,
          "is_total": 0,
          "is_exemption": 0,
          "is_continued": 0
        },
        {
          "mr": "27",
          "townland": "",
          "os": "",
          "sublocation_1": "",
          "sublocation_2": "",
          "occupier": "Johanna M‘Namara",
          "lessor": "Timothy Murphy",
          "desc": "H,&yard,&G",
          "area": "0 0 11",
          "land_val": "0 3 0",
          "building_val": "1 0 0",
          "total_val": "1 3 0",
          "n_shared": 1,
          "is_total": 0,
          "is_exemption": 0,
          "is_continued": 0
        },
        {
          "mr": "28",
          "townland": "",
          "os": "",
          "sublocation_1": "",
          "sublocation_2": "",
          "occupier": "Viscount Doneraile",
          "lessor": "In fee",
          "desc": "Garden",
          "area": "0 0 19",
          "land_val": "0 4 0",
          "building_val": "",
          "total_val": "0 4 0",
          "n_shared": 1,
          "is_total": 0,
          "is_exemption": 0,
          "is_continued": 0
        },
        {
          "mr": "29",
          "townland": "",
          "os": "",
          "sublocation_1": "",
          "sublocation_2": "",
          "occupier": "Patrick Hickey",
          "lessor": "Viscount Doneraile",
          "desc": "H,&yard,&G",
          "area": "0 0 10",
          "land_val": "0 3 0",
          "building_val": "1 7 0",
          "total_val": "1 10 0",
          "n_shared": 1,
          "is_total": 0,
          "is_exemption": 0,
          "is_continued": 0
        },
        {
          "mr": "30",
          "townland": "",
          "os": "",
          "sublocation_1": "",
          "sublocation_2": "",
          "occupier": "James Ahern",
          "lessor": "Patrick Hickey",
          "desc": "H",
          "area": "",
          "land_val": "",
          "building_val": "0 14 0",
          "total_val": "0 14 0",
          "n_shared": 1,
          "is_total": 0,
          "is_exemption": 0,
          "is_continued": 0
        },
        {
          "mr": "31",
          "townland": "",
          "os": "",
          "sublocation_1": "",
          "sublocation_2": "",
          "occupier": "Patrick Guiney",
          "lessor": "Patrick Hickey",
          "desc": "H",
          "area": "",
          "land_val": "",
          "building_val": "0 18 0",
          "total_val": "0 18 0",
          "n_shared": 2,
          "is_total": 0,
          "is_exemption": 0,
          "is_continued": 0
        },
        {
          "mr": "31",
          "townland": "",
          "os": "",
          "sublocation_1": "",
          "sublocation_2": "",
          "occupier": "Timothy Quinlon",
          "lessor": "Patrick Hickey",
          "desc": "H",
          "area": "",
          "land_val": "",
          "building_val": "0 18 0",
          "total_val": "0 18 0",
          "n_shared": 2,
          "is_total": 0,
          "is_exemption": 0,
          "is_continued": 0
        },
        {
          "mr": "32",
          "townland": "",
          "os": "",
          "sublocation_1": "",
          "sublocation_2": "",
          "occupier": "Viscount Doneraile",
          "lessor": "In fee",
          "desc": "Garden",
          "area": "0 0 11",
          "land_val": "0 2 0",
          "building_val": "",
          "total_val": "0 2 0",
          "n_shared": 1,
          "is_total": 0,
          "is_exemption": 0,
          "is_continued": 0
        },
        {
          "mr": "33",
          "townland": "",
          "os": "",
          "sublocation_1": "",
          "sublocation_2": "",
          "occupier": "Eliza M‘Carthy",
          "lessor": "George Kerr",
          "desc": "H",
          "area": "",
          "land_val": "",
          "building_val": "0 10 0",
          "total_val": "0 10 0",
          "n_shared": 1,
          "is_total": 0,
          "is_exemption": 0,
          "is_continued": 0
        },
        {
          "mr": "34",
          "townland": "",
          "os": "",
          "sublocation_1": "",
          "sublocation_2": "",
          "occupier": "John Lehane",
          "lessor": "George Kerr",
          "desc": "H",
          "area": "",
          "land_val": "",
          "building_val": "0 14 0",
          "total_val": "0 14 0",
          "n_shared": 1,
          "is_total": 0,
          "is_exemption": 0,
          "is_continued": 0
        },
        {
          "mr": "35",
          "townland": "",
          "os": "",
          "sublocation_1": "",
          "sublocation_2": "",
          "occupier": "James Dogherty",
          "lessor": "Viscount Doneraile",
          "desc": "H,&yard,&G",
          "area": "0 0 13",
          "land_val": "0 3 0",
          "building_val": "1 5 0",
          "total_val": "1 8 0",
          "n_shared": 1,
          "is_total": 0,
          "is_exemption": 0,
          "is_continued": 0
        },
        {
          "mr": "36",
          "townland": "",
          "os": "",
          "sublocation_1": "",
          "sublocation_2": "",
          "occupier": "Edward Linehan",
          "lessor": "George Kerr",
          "desc": "H,&yard,&G",
          "area": "0 0 10",
          "land_val": "0 2 0",
          "building_val": "0 14 0",
          "total_val": "0 16 0",
          "n_shared": 1,
          "is_total": 0,
          "is_exemption": 0,
          "is_continued": 0
        },
        {
          "mr": "37",
          "townland": "",
          "os": "",
          "sublocation_1": "",
          "sublocation_2": "",
          "occupier": "Daniel Sheehan",
          "lessor": "James Daly",
          "desc": "H",
          "area": "",
          "land_val": "",
          "building_val": "1 5 0",
          "total_val": "1 5 0",
          "n_shared": 1,
          "is_total": 0,
          "is_exemption": 0,
          "is_continued": 0
        },
        {
          "mr": "38",
          "townland": "",
          "os": "",
          "sublocation_1": "",
          "sublocation_2": "",
          "occupier": "James Daly",
          "lessor": "Viscount Doneraile",
          "desc": "H,&yard,&G",
          "area": "0 0 19",
          "land_val": "0 5 0",
          "building_val": "1 5 0",
          "total_val": "1 10 0",
          "n_shared": 1,
          "is_total": 0,
          "is_exemption": 0,
          "is_continued": 0
        },
        {
          "mr": "39",
          "townland": "",
          "os": "",
          "sublocation_1": "",
          "sublocation_2": "",
          "occupier": "Honoria Hampstill",
          "lessor": "Roger M‘Carthy",
          "desc": "H",
          "area": "",
          "land_val": "",
          "building_val": "1 2 0",
          "total_val": "1 2 0",
          "n_shared": 1,
          "is_total": 0,
          "is_exemption": 0,
          "is_continued": 0
        },
        {
          "mr": "40",
          "townland": "",
          "os": "",
          "sublocation_1": "",
          "sublocation_2": "",
          "occupier": "Roger M‘Carthy",
          "lessor": "Viscount Doneraile",
          "desc": "H,&yard,&G",
          "area": "0 0 26",
          "land_val": "0 5 0",
          "building_val": "0 18 0",
          "total_val": "1 3 0",
          "n_shared": 1,
          "is_total": 0,
          "is_exemption": 0,
          "is_continued": 0
        },
        {
          "mr": "41",
          "townland": "",
          "os": "",
          "sublocation_1": "",
          "sublocation_2": "",
          "occupier": "John Dougan",
          "lessor": "Roger M‘Carthy",
          "desc": "H",
          "area": "",
          "land_val": "",
          "building_val": "0 16 0",
          "total_val": "0 16 0",
          "n_shared": 1,
          "is_total": 0,
          "is_exemption": 0,
          "is_continued": 0
        },
        {
          "mr": "42",
          "townland": "",
          "os": "",
          "sublocation_1": "",
          "sublocation_2": "",
          "occupier": "Jeremiah Keefe",
          "lessor": "Viscount Doneraile",
          "desc": "H&G",
          "area": "0 0 13",
          "land_val": "0 3 0",
          "building_val": "0 18 0",
          "total_val": "1 1 0",
          "n_shared": 1,
          "is_total": 0,
          "is_exemption": 0,
          "is_continued": 0
        },
        {
          "mr": "43",
          "townland": "",
          "os": "",
          "sublocation_1": "",
          "sublocation_2": "",
          "occupier": "Viscount Doneraile",
          "lessor": "In fee",
          "desc": "Garden",
          "area": "0 0 11",
          "land_val": "0 2 0",
          "building_val": "",
          "total_val": "0 2 0",
          "n_shared": 1,
          "is_total": 0,
          "is_exemption": 0,
          "is_continued": 0
        },
        {
          "mr": "44",
          "townland": "",
          "os": "",
          "sublocation_1": "",
          "sublocation_2": "",
          "occupier": "Barthw. M‘Carthy",
          "lessor": "Timothy Murphy",
          "desc": "H",
          "area": "",
          "land_val": "",
          "building_val": "1 0 0",
          "total_val": "1 0 0",
          "n_shared": 1,
          "is_total": 0,
          "is_exemption": 0,
          "is_continued": 0
        },
        {
          "mr": "45",
          "townland": "",
          "os": "",
          "sublocation_1": "",
          "sublocation_2": "",
          "occupier": "Edward Mullane",
          "lessor": "Timothy Murphy",
          "desc": "H",
          "area": "",
          "land_val": "",
          "building_val": "1 0 0",
          "total_val": "1 0 0",
          "n_shared": 1,
          "is_total": 0,
          "is_exemption": 0,
          "is_continued": 0
        },
        {
          "mr": "46",
          "townland": "",
          "os": "",
          "sublocation_1": "",
          "sublocation_2": "",
          "occupier": "Timothy Murphy",
          "lessor": "Viscount Doneraile",
          "desc": "L",
          "area": "0 0 21",
          "land_val": "0 5 0",
          "building_val": "",
          "total_val": "0 5 0",
          "n_shared": 1,
          "is_total": 0,
          "is_exemption": 0,
          "is_continued": 0
        },
        {
          "mr": "1",
          "townland": "",
          "os": "",
          "sublocation_1": "BARRACK-PLACE",
          "sublocation_2": "",
          "occupier": "John Reilly",
          "lessor": "Viscount Doneraile",
          "desc": "H",
          "area": "",
          "land_val": "",
          "building_val": "1 5 0",
          "total_val": "1 5 0",
          "n_shared": 2,
          "is_total": 0,
          "is_exemption": 0,
          "is_continued": 0
        },
        {
          "mr": "1",
          "townland": "",
          "os": "",
          "sublocation_1": "",
          "sublocation_2": "",
          "occupier": "Patrick Quinlan",
          "lessor": "Viscount Doneraile",
          "desc": "H",
          "area": "",
          "land_val": "",
          "building_val": "1 5 0",
          "total_val": "1 5 0",
          "n_shared": 2,
          "is_total": 0,
          "is_exemption": 0,
          "is_continued": 0
        },
        {
          "mr": "2",
          "townland": "",
          "os": "",
          "sublocation_1": "",
          "sublocation_2": "",
          "occupier": "Thomas Harris",
          "lessor": "Viscount Doneraile",
          "desc": "H",
          "area": "",
          "land_val": "",
          "building_val": "0 15 0",
          "total_val": "0 15 0",
          "n_shared": 1,
          "is_total": 0,
          "is_exemption": 0,
          "is_continued": 0
        },
        {
          "mr": "3",
          "townland": "",
          "os": "",
          "sublocation_1": "",
          "sublocation_2": "",
          "occupier": "James Regan",
          "lessor": "Viscount Doneraile",
          "desc": "H",
          "area": "",
          "land_val": "",
          "building_val": "0 10 0",
          "total_val": "0 10 0",
          "n_shared": 1,
          "is_total": 0,
          "is_exemption": 0,
          "is_continued": 0
        },
        {
          "mr": "4",
          "townland": "",
          "os": "",
          "sublocation_1": "",
          "sublocation_2": "",
          "occupier": "Michael Doherty",
          "lessor": "Michael M‘Donnell",
          "desc": "H&yard",
          "area": "",
          "land_val": "",
          "building_val": "0 12 0",
          "total_val": "0 12 0",
          "n_shared": 1,
          "is_total": 0,
          "is_exemption": 0,
          "is_continued": 0
        },
        {
          "mr": "5",
          "townland": "",
          "os": "",
          "sublocation_1": "",
          "sublocation_2": "",
          "occupier": "Patrick Buckley",
          "lessor": "Viscount Doneraile",
          "desc": "H",
          "area": "",
          "land_val": "",
          "building_val": "0 14 0",
          "total_val": "0 14 0",
          "n_shared": 1,
          "is_total": 0,
          "is_exemption": 0,
          "is_continued": 0
        },
        {
          "mr": "6",
          "townland": "",
          "os": "",
          "sublocation_1": "",
          "sublocation_2": "",
          "occupier": "Michael Green",
          "lessor": "Viscount Doneraile",
          "desc": "H",
          "area": "",
          "land_val": "",
          "building_val": "0 16 0",
          "total_val": "0 16 0",
          "n_shared": 1,
          "is_total": 0,
          "is_exemption": 0,
          "is_continued": 0
        },
        {
          "mr": "7",
          "townland": "",
          "os": "",
          "sublocation_1": "",
          "sublocation_2": "",
          "occupier": "Viscount Doneraile",
          "lessor": "In fee",
          "desc": "Building site (waste)",
          "area": "0 0 5",
          "land_val": "",
          "building_val": "",
          "total_val": "",
          "n_shared": 1,
          "is_total": 0,
          "is_exemption": 0,
          "is_continued": 0
        }
      ]
    }
  ]
}