{
  "parishes": [
    {
      "parish": "RATHGOGGAN",
      "entries": [
        {
          "mr": "5",
          "townland": "RATHGOGGAN MIDDLE",
          "os": "",
          "sublocation_1": "TOWN OF CHARLEVILLE",
          "sublocation_2": "COSNOR'S-LANE",
          "occupier": "Unoccupied",
          "lessor": "Daniel Clanchy, Esq.",
          "desc": "H",
          "area": "",
          "land_val": "",
          "building_val": "1 2 0",
          "total_val": "1 2 0",
          "n_shared": 1,
          "is_total": 0,
          "is_exemption": 0,
          "is_continued": 1
        },
        {
          "mr": "6",
          "townland": "",
          "os": "",
          "sublocation_1": "",
          "sublocation_2": "",
          "occupier": "Ellen Grady",
          "lessor": "Mrs. O'Keeffe",
          "desc": "H",
          "area": "",
          "land_val": "",
          "building_val": "0 10 0",
          "total_val": "0 10 0",
          "n_shared": 1,
          "is_total": 0,
          "is_exemption": 0,
          "is_continued": 0
        },
        {
          "mr": "7",
          "townland": "",
          "os": "",
          "sublocation_1": "",
          "sublocation_2": "",
          "occupier": "Mary Walsh",
          "lessor": "William Crea",
          "desc": "H & small garden",
          "area": "",
          "land_val": "",
          "building_val": "1 10 0",
          "total_val": "1 10 0",
          "n_shared": 1,
          "is_total": 0,
          "is_exemption": 0,
          "is_continued": 0
        },
        {
          "mr": "8",
          "townland": "",
          "os": "",
          "sublocation_1": "",
          "sublocation_2": "",
          "occupier": "Patrick Regan",
          "lessor": "Mrs. O'Keeffe",
          "desc": "H",
          "area": "",
          "land_val": "",
          "building_val": "0 16 0",
          "total_val": "0 16 0",
          "n_shared": 1,
          "is_total": 0,
          "is_exemption": 0,
          "is_continued": 0
        },
        {
          "mr": "9",
          "townland": "",
          "os": "",
          "sublocation_1": "",
          "sublocation_2": "",
          "occupier": "Unoccupied",
          "lessor": "Mrs. O'Keeffe",
          "desc": "H",
          "area": "",
          "land_val": "",
          "building_val": "0 14 0",
          "total_val": "0 14 0",
          "n_shared": 1,
          "is_total": 0,
          "is_exemption": 0,
          "is_continued": 0
        },
        {
          "mr": "1",
          "townland": "",
          "os": "",
          "sublocation_1": "",
          "sublocation_2": "CORK-ROAD",
          "occupier": "Michael Sweeny",
          "lessor": "Daniel Clanchy, Esq.",
          "desc": "H",
          "area": "",
          "land_val": "",
          "building_val": "1 4 0",
          "total_val": "1 4 0",
          "n_shared": 1,
          "is_total": 0,
          "is_exemption": 0,
          "is_continued": 0
        },
        {
          "mr": "2",
          "townland": "",
          "os": "",
          "sublocation_1": "",
          "sublocation_2": "",
          "occupier": "Daniel O'Brien",
          "lessor": "William Crea",
          "desc": "H",
          "area": "",
          "land_val": "",
          "building_val": "2 0 0",
          "total_val": "2 0 0",
          "n_shared": 1,
          "is_total": 0,
          "is_exemption": 0,
          "is_continued": 0
        },
        {
          "mr": "3",
          "townland": "",
          "os": "",
          "sublocation_1": "",
          "sublocation_2": "",
          "occupier": "Margaret Connell",
          "lessor": "Daniel Clanchy, Esq.",
          "desc": "H and yard",
          "area": "",
          "land_val": "",
          "building_val": "3 10 0",
          "total_val": "3 10 0",
          "n_shared": 1,
          "is_total": 0,
          "is_exemption": 0,
          "is_continued": 0
        },
        {
          "mr": "4",
          "townland": "",
          "os": "",
          "sublocation_1": "",
          "sublocation_2": "",
          "occupier": "William Creagh",
          "lessor": "Daniel Clanchy, Esq.",
          "desc": "H and yard",
          "area": "",
          "land_val": "",
          "building_val": "4 5 0",
          "total_val": "4 5 0",
          "n_shared": 1,
          "is_total": 0,
          "is_exemption": 0,
          "is_continued": 0
        },
        {
          "mr": "5",
          "townland": "",
          "os": "",
          "sublocation_1": "",
          "sublocation_2": "",
          "occupier": "John Connor",
          "lessor": "James Duffy",
          "desc": "H, O, and yard",
          "area": "",
          "land_val": "",
          "building_val": "4 10 0",
          "total_val": "4 10 0",
          "n_shared": 1,
          "is_total": 0,
          "is_exemption": 0,
          "is_continued": 0
        },
        {
          "mr": "6",
          "townland": "",
          "os": "",
          "sublocation_1": "",
          "sublocation_2": "",
          "occupier": "Unoccupied",
          "lessor": "James Duffy",
          "desc": "H, O, and yard",
          "area": "",
          "land_val": "",
          "building_val": "4 10 0",
          "total_val": "4 10 0",
          "n_shared": 1,
          "is_total": 0,
          "is_exemption": 0,
          "is_continued": 0
        },
        {
          "mr": "7",
          "townland": "",
          "os": "",
          "sublocation_1": "",
          "sublocation_2": "",
          "occupier": "Catherine O'Keeffe",
          "lessor": "Daniel Clanchy, Esq.",
          "desc": "H, O, and yard",
          "area": "",
          "land_val": "",
          "building_val": "8 10 0",
          "total_val": "8 10 0",
          "n_shared": 1,
          "is_total": 0,
          "is_exemption": 0,
          "is_continued": 0
        },
        {
          "mr": "8",
          "townland": "",
          "os": "",
          "sublocation_1": "",
          "sublocation_2": "",
          "occupier": "James Desmond",
          "lessor": "Catherine O'Keeffe",
          "desc": "H",
          "area": "",
          "land_val": "",
          "building_val": "1 15 0",
          "total_val": "1 15 0",
          "n_shared": 1,
          "is_total": 0,
          "is_exemption": 0,
          "is_continued": 0
        },
        {
          "mr": "9",
          "townland": "",
          "os": "",
          "sublocation_1": "",
          "sublocation_2": "",
          "occupier": "John Shaughnessy",
          "lessor": "Roger O'Gorman",
          "desc": "H, O, & sm. gar.",
          "area": "",
          "land_val": "",
          "building_val": "5 0 0",
          "total_val": "5 0 0",
          "n_shared": 1,
          "is_total": 0,
          "is_exemption": 0,
          "is_continued": 0
        },
        {
          "mr": "10",
          "townland": "",
          "os": "",
          "sublocation_1": "",
          "sublocation_2": "",
          "occupier": "John Duane",
          "lessor": "Daniel Clanchy, Esq.",
          "desc": "H, O, & sm. gar.",
          "area": "",
          "land_val": "",
          "building_val": "4 15 0",
          "total_val": "4 15 0",
          "n_shared": 1,
          "is_total": 0,
          "is_exemption": 0,
          "is_continued": 0
        },
        {
          "mr": "11",
          "townland": "",
          "os": "",
          "sublocation_1": "",
          "sublocation_2": "",
          "occupier": "Daniel Clanchy, Esq.",
          "lessor": "Earl of Cork",
          "desc": "G",
          "area": "0 2 37",
          "land_val": "2 0 0",
          "building_val": "",
          "total_val": "2 0 0",
          "n_shared": 1,
          "is_total": 0,
          "is_exemption": 0,
          "is_continued": 0
        },
        {
          "mr": "12",
          "townland": "",
          "os": "",
          "sublocation_1": "",
          "sublocation_2": "",
          "occupier": "John Lee",
          "lessor": "John Ryan, Esq.",
          "desc": "H, O, & yd. & sm. gar.",
          "area": "",
          "land_val": "",
          "building_val": "2 15 0",
          "total_val": "2 15 0",
          "n_shared": 1,
          "is_total": 0,
          "is_exemption": 0,
          "is_continued": 0
        },
        {
          "mr": "13",
          "townland": "",
          "os": "",
          "sublocation_1": "",
          "sublocation_2": "",
          "occupier": "Denis Cronin",
          "lessor": "John Ryan, Esq.",
          "desc": "H, O, and yard",
          "area": "",
          "land_val": "",
          "building_val": "3 10 0",
          "total_val": "3 10 0",
          "n_shared": 1,
          "is_total": 0,
          "is_exemption": 0,
          "is_continued": 0
        },
        {
          "mr": "14",
          "townland": "",
          "os": "",
          "sublocation_1": "",
          "sublocation_2": "",
          "occupier": "Patrick Meade",
          "lessor": "Denis Cronin",
          "desc": "H",
          "area": "",
          "land_val": "",
          "building_val": "1 5 0",
          "total_val": "1 5 0",
          "n_shared": 1,
          "is_total": 0,
          "is_exemption": 0,
          "is_continued": 0
        },
        {
          "mr": "15",
          "townland": "",
          "os": "",
          "sublocation_1": "",
          "sublocation_2": "",
          "occupier": "Timothy Connell",
          "lessor": "John Ryan, Esq.",
          "desc": "H and garden",
          "area": "0 0 14",
          "land_val": "0 5 0",
          "building_val": "2 0 0",
          "total_val": "2 5 0",
          "n_shared": 1,
          "is_total": 0,
          "is_exemption": 0,
          "is_continued": 0
        },
        {
          "mr": "16",
          "townland": "",
          "os": "",
          "sublocation_1": "",
          "sublocation_2": "",
          "occupier": "John Ryan, Esq.",
          "lessor": "Earl of Cork",
          "desc": "G",
          "area": "0 0 16",
          "land_val": "0 4 0",
          "building_val": "",
          "total_val": "0 4 0",
          "n_shared": 1,
          "is_total": 0,
          "is_exemption": 0,
          "is_continued": 0
        },
        {
          "mr": "17",
          "townland": "",
          "os": "",
          "sublocation_1": "",
          "sublocation_2": "",
          "occupier": "Denis Regan",
          "lessor": "John Ryan, Esq.",
          "desc": "H, O, and yard",
          "area": "",
          "land_val": "",
          "building_val": "3 0 0",
          "total_val": "3 0 0",
          "n_shared": 1,
          "is_total": 0,
          "is_exemption": 0,
          "is_continued": 0
        },
        {
          "mr": "18",
          "townland": "",
          "os": "",
          "sublocation_1": "",
          "sublocation_2": "",
          "occupier": "Matthew Broughton",
          "lessor": "John Ryan, Esq.",
          "desc": "Office",
          "area": "",
          "land_val": "",
          "building_val": "1 0 0",
          "total_val": "1 0 0",
          "n_shared": 1,
          "is_total": 0,
          "is_exemption": 0,
          "is_continued": 0
        },
        {
          "mr": "19",
          "townland": "",
          "os": "",
          "sublocation_1": "",
          "sublocation_2": "",
          "occupier": "Unoccupied",
          "lessor": "Matthew Broughton",
          "desc": "H",
          "area": "",
          "land_val": "",
          "building_val": "0 18 0",
          "total_val": "0 18 0",
          "n_shared": 1,
          "is_total": 0,
          "is_exemption": 0,
          "is_continued": 0
        },
        {
          "mr": "20",
          "townland": "",
          "os": "",
          "sublocation_1": "",
          "sublocation_2": "",
          "occupier": "Mary Kelly",
          "lessor": "Richard Daly, Esq.",
          "desc": "H",
          "area": "",
          "land_val": "",
          "building_val": "0 15 0",
          "total_val": "0 15 0",
          "n_shared": 1,
          "is_total": 0,
          "is_exemption": 0,
          "is_continued": 0
        },
        {
          "mr": "21",
          "townland": "",
          "os": "",
          "sublocation_1": "",
          "sublocation_2": "",
          "occupier": "Unoccupied",
          "lessor": "Daniel Clanchy, Esq.",
          "desc": "H and yard",
          "area": "",
          "land_val": "",
          "building_val": "2 15 0",
          "total_val": "2 15 0",
          "n_shared": 1,
          "is_total": 0,
          "is_exemption": 0,
          "is_continued": 0
        },
        {
          "mr": "22",
          "townland": "",
          "os": "",
          "sublocation_1": "",
          "sublocation_2": "",
          "occupier": "Unoccupied",
          "lessor": "Daniel Clanchy, Esq.",
          "desc": "H and yard",
          "area": "",
          "land_val": "",
          "building_val": "2 15 0",
          "total_val": "2 15 0",
          "n_shared": 1,
          "is_total": 0,
          "is_exemption": 0,
          "is_continued": 0
        },
        {
          "mr": "23",
          "townland": "",
          "os": "",
          "sublocation_1": "",
          "sublocation_2": "",
          "occupier": "William Burke",
          "lessor": "Daniel Clanchy, Esq.",
          "desc": "H and yard",
          "area": "",
          "land_val": "",
          "building_val": "2 15 0",
          "total_val": "2 15 0",
          "n_shared": 1,
          "is_total": 0,
          "is_exemption": 0,
          "is_continued": 0
        },
        {
          "mr": "24",
          "townland": "",
          "os": "",
          "sublocation_1": "",
          "sublocation_2": "",
          "occupier": "Unoccupied",
          "lessor": "Daniel Clanchy, Esq.",
          "desc": "H and yard",
          "area": "",
          "land_val": "",
          "building_val": "2 15 0",
          "total_val": "2 15 0",
          "n_shared": 1,
          "is_total": 0,
          "is_exemption": 0,
          "is_continued": 0
        },
        {
          "mr": "25",
          "townland": "",
          "os": "",
          "sublocation_1": "",
          "sublocation_2": "",
          "occupier": "John Hurly",
          "lessor": "Daniel Clanchy, Esq.",
          "desc": "H, O, and yard",
          "area": "",
          "land_val": "",
          "building_val": "3 0 0",
          "total_val": "3 0 0",
          "n_shared": 1,
          "is_total": 0,
          "is_exemption": 0,
          "is_continued": 0
        },
        {
          "mr": "26",
          "townland": "",
          "os": "",
          "sublocation_1": "",
          "sublocation_2": "",
          "occupier": "Ellen Connell",
          "lessor": "Kennedy Ryan, Esq.",
          "desc": "H",
          "area": "",
          "land_val": "",
          "building_val": "1 10 0",
          "total_val": "1 10 0",
          "n_shared": 1,
          "is_total": 0,
          "is_exemption": 0,
          "is_continued": 0
        },
        {
          "mr": "27",
          "townland": "",
          "os": "",
          "sublocation_1": "",
          "sublocation_2": "",
          "occupier": "Michael Kennedy",
          "lessor": "Kennedy Ryan, Esq.",
          "desc": "H and office",
          "area": "",
          "land_val": "",
          "building_val": "2 15 0",
          "total_val": "2 15 0",
          "n_shared": 1,
          "is_total": 0,
          "is_exemption": 0,
          "is_continued": 0
        },
        {
          "mr": "28",
          "townland": "",
          "os": "",
          "sublocation_1": "",
          "sublocation_2": "",
          "occupier": "James Murphy",
          "lessor": "Kennedy Ryan, Esq.",
          "desc": "H and small gar.",
          "area": "",
          "land_val": "",
          "building_val": "1 15 0",
          "total_val": "1 15 0",
          "n_shared": 1,
          "is_total": 0,
          "is_exemption": 0,
          "is_continued": 0
        },
        {
          "mr": "29",
          "townland": "",
          "os": "",
          "sublocation_1": "",
          "sublocation_2": "",
          "occupier": "John Wallace",
          "lessor": "Kennedy Ryan, Esq.",
          "desc": "H and small gar.",
          "area": "",
          "land_val": "",
          "building_val": "1 10 0",
          "total_val": "1 10 0",
          "n_shared": 1,
          "is_total": 0,
          "is_exemption": 0,
          "is_continued": 0
        },
        {
          "mr": "30",
          "townland": "",
          "os": "",
          "sublocation_1": "",
          "sublocation_2": "",
          "occupier": "Michael Dunworth",
          "lessor": "Kennedy Ryan, Esq.",
          "desc": "H and small gar.",
          "area": "",
          "land_val": "",
          "building_val": "1 5 0",
          "total_val": "1 5 0",
          "n_shared": 1,
          "is_total": 0,
          "is_exemption": 0,
          "is_continued": 0
        },
        {
          "mr": "1",
          "townland": "DARGAN'S-LANE",
          "os": "",
          "sublocation_1": "",
          "sublocation_2": "",
          "occupier": "William Connolly",
          "lessor": "John Ryan, Esq. and Richard Daly,",
          "desc": "H",
          "area": "",
          "land_val": "",
          "building_val": "0 18 0",
          "total_val": "0 18 0",
          "n_shared": 1,
          "is_total": 0,
          "is_exemption": 0,
          "is_continued": 0
        },
        {
          "mr": "2",
          "townland": "",
          "os": "",
          "sublocation_1": "",
          "sublocation_2": "",
          "occupier": "John Dunn",
          "lessor": "John Ryan, Esq. and Richard Daly,",
          "desc": "H",
          "area": "",
          "land_val": "",
          "building_val": "0 12 0",
          "total_val": "0 12 0",
          "n_shared": 1,
          "is_total": 0,
          "is_exemption": 0,
          "is_continued": 0
        },
        {
          "mr": "3",
          "townland": "",
          "os": "",
          "sublocation_1": "",
          "sublocation_2": "",
          "occupier": "Michael Sweeney",
          "lessor": "John Ryan, Esq. and Richard Daly,",
          "desc": "H",
          "area": "",
          "land_val": "",
          "building_val": "0 12 0",
          "total_val": "0 12 0",
          "n_shared": 1,
          "is_total": 0,
          "is_exemption": 0,
          "is_continued": 0
        },
        {
          "mr": "4",
          "townland": "",
          "os": "",
          "sublocation_1": "",
          "sublocation_2": "",
          "occupier": "Jeremiah Brien",
          "lessor": "Honoria Corbett",
          "desc": "H and yard",
          "area": "",
          "land_val": "",
          "building_val": "0 15 0",
          "total_val": "0 15 0",
          "n_shared": 1,
          "is_total": 0,
          "is_exemption": 0,
          "is_continued": 0
        },
        {
          "mr": "5",
          "townland": "",
          "os": "",
          "sublocation_1": "",
          "sublocation_2": "",
          "occupier": "Patrick Quinlan",
          "lessor": "Honoria Corbett",
          "desc": "H and yard",
          "area": "",
          "land_val": "",
          "building_val": "0 18 0",
          "total_val": "0 18 0",
          "n_shared": 1,
          "is_total": 0,
          "is_exemption": 0,
          "is_continued": 0
        },
        {
          "mr": "6",
          "townland": "",
          "os": "",
          "sublocation_1": "",
          "sublocation_2": "",
          "occupier": "William Buckley",
          "lessor": "Honoria Corbett",
          "desc": "H",
          "area": "",
          "land_val": "",
          "building_val": "0 18 0",
          "total_val": "0 18 0",
          "n_shared": 1,
          "is_total": 0,
          "is_exemption": 0,
          "is_continued": 0
        },
        {
          "mr": "7",
          "townland": "",
          "os": "",
          "sublocation_1": "",
          "sublocation_2": "",
          "occupier": "Daniel Sullivan",
          "lessor": "Andrew Creed",
          "desc": "H",
          "area": "",
          "land_val": "",
          "building_val": "0 18 0",
          "total_val": "0 18 0",
          "n_shared": 1,
          "is_total": 0,
          "is_exemption": 0,
          "is_continued": 0
        },
        {
          "mr": "8",
          "townland": "",
          "os": "",
          "sublocation_1": "",
          "sublocation_2": "",
          "occupier": "Jeremiah M'Carthy",
          "lessor": "Jeremiah Cranwich",
          "desc": "H",
          "area": "",
          "land_val": "",
          "building_val": "0 15 0",
          "total_val": "0 15 0",
          "n_shared": 1,
          "is_total": 0,
          "is_exemption": 0,
          "is_continued": 0
        },
        {
          "mr": "9",
          "townland": "",
          "os": "",
          "sublocation_1": "",
          "sublocation_2": "",
          "occupier": "Honoria Connell",
          "lessor": "Jeremiah Cranwich",
          "desc": "H",
          "area": "",
          "land_val": "",
          "building_val": "0 15 0",
          "total_val": "0 15 0",
          "n_shared": 1,
          "is_total": 0,
          "is_exemption": 0,
          "is_continued": 0
        },
        {
          "mr": "10",
          "townland": "",
          "os": "",
          "sublocation_1": "",
          "sublocation_2": "",
          "occupier": "Daniel Riordan",
          "lessor": "Jeremiah Cranwich",
          "desc": "H",
          "area": "",
          "land_val": "",
          "building_val": "0 18 0",
          "total_val": "0 18 0",
          "n_shared": 1,
          "is_total": 0,
          "is_exemption": 0,
          "is_continued": 0
        },
        {
          "mr": "11",
          "townland": "",
          "os": "",
          "sublocation_1": "",
          "sublocation_2": "",
          "occupier": "John Foley",
          "lessor": "Jeremiah Cranwich",
          "desc": "H",
          "area": "",
          "land_val": "",
          "building_val": "0 18 0",
          "total_val": "0 18 0",
          "n_shared": 1,
          "is_total": 0,
          "is_exemption": 0,
          "is_continued": 0
        },
        {
          "mr": "12",
          "townland": "",
          "os": "",
          "sublocation_1": "",
          "sublocation_2": "",
          "occupier": "Maurice Barry",
          "lessor": "Jeremiah Cranwich",
          "desc": "H",
          "area": "",
          "land_val": "",
          "building_val": "0 18 0",
          "total_val": "0 18 0",
          "n_shared": 1,
          "is_total": 0,
          "is_exemption": 0,
          "is_continued": 0
        },
        {
          "mr": "13",
          "townland": "",
          "os": "",
          "sublocation_1": "",
          "sublocation_2": "",
          "occupier": "Unoccupied",
          "lessor": "Jeremiah Cranwich",
          "desc": "H",
          "area": "",
          "land_val": "",
          "building_val": "1 0 0",
          "total_val": "1 0 0",
          "n_shared": 1,
          "is_total": 0,
          "is_exemption": 0,
          "is_continued": 0
        },
        {
          "mr": "1",
          "townland": "CLANCY'S-LANE",
          "os": "",
          "sublocation_1": "",
          "sublocation_2": "",
          "occupier": "Thomas Grady",
          "lessor": "Richard Daly",
          "desc": "H and G",
          "area": "0 0 16",
          "land_val": "0 5 0",
          "building_val": "2 15 0",
          "total_val": "3 0 0",
          "n_shared": 1,
          "is_total": 0,
          "is_exemption": 0,
          "is_continued": 0
        },
        {
          "mr": "2",
          "townland": "",
          "os": "",
          "sublocation_1": "",
          "sublocation_2": "",
          "occupier": "Timothy Hoonaghan",
          "lessor": "Richard Daly",
          "desc": "H",
          "area": "",
          "land_val": "",
          "building_val": "1 10 0",
          "total_val": "1 10 0",
          "n_shared": 1,
          "is_total": 0,
          "is_exemption": 0,
          "is_continued": 0
        },
        {
          "mr": "3",
          "townland": "",
          "os": "",
          "sublocation_1": "",
          "sublocation_2": "",
          "occupier": "Michael Brannon",
          "lessor": "James Doyle",
          "desc": "H & small garden",
          "area": "",
          "land_val": "",
          "building_val": "1 10 0",
          "total_val": "1 10 0",
          "n_shared": 1,
          "is_total": 0,
          "is_exemption": 0,
          "is_continued": 0
        },
        {
          "mr": "4",
          "townland": "",
          "os": "",
          "sublocation_1": "",
          "sublocation_2": "",
          "occupier": "Mary M'Namara",
          "lessor": "James Doyle",
          "desc": "H & small garden",
          "area": "",
          "land_val": "",
          "building_val": "1 4 0",
          "total_val": "1 4 0",
          "n_shared": 1,
          "is_total": 0,
          "is_exemption": 0,
          "is_continued": 0
        },
        {
          "mr": "1",
          "townland": "BRIDEWELL-LANE",
          "os": "",
          "sublocation_1": "",
          "sublocation_2": "",
          "occupier": "Honoria Griffin",
          "lessor": "Edward Fox",
          "desc": "H",
          "area": "",
          "land_val": "",
          "building_val": "1 4 0",
          "total_val": "1 4 0",
          "n_shared": 1,
          "is_total": 0,
          "is_exemption": 0,
          "is_continued": 0
        },
        {
          "mr": "2",
          "townland": "",
          "os": "",
          "sublocation_1": "",
          "sublocation_2": "",
          "occupier": "William Brien",
          "lessor": "Daniel Clanchy, Esq.",
          "desc": "H",
          "area": "",
          "land_val": "",
          "building_val": "1 2 0",
          "total_val": "1 2 0",
          "n_shared": 1,
          "is_total": 0,
          "is_exemption": 0,
          "is_continued": 0
        },
        {
          "mr": "3",
          "townland": "",
          "os": "",
          "sublocation_1": "",
          "sublocation_2": "",
          "occupier": "William Driscoll",
          "lessor": "Daniel Clanchy, Esq.",
          "desc": "H",
          "area": "",
          "land_val": "",
          "building_val": "0 18 0",
          "total_val": "0 18 0",
          "n_shared": 1,
          "is_total": 0,
          "is_exemption": 0,
          "is_continued": 0
        },
        {
          "mr": "4",
          "townland": "",
          "os": "",
          "sublocation_1": "",
          "sublocation_2": "",
          "occupier": "Thaddeus Gully",
          "lessor": "Daniel Clanchy, Esq.",
          "desc": "H",
          "area": "",
          "land_val": "",
          "building_val": "1 2 0",
          "total_val": "1 2 0",
          "n_shared": 1,
          "is_total": 0,
          "is_exemption": 0,
          "is_continued": 0
        },
        {
          "mr": "5",
          "townland": "",
          "os": "",
          "sublocation_1": "",
          "sublocation_2": "",
          "occupier": "Patrick Connell",
          "lessor": "Daniel Clanchy, Esq.",
          "desc": "H",
          "area": "",
          "land_val": "",
          "building_val": "0 18 0",
          "total_val": "0 18 0",
          "n_shared": 1,
          "is_total": 0,
          "is_exemption": 0,
          "is_continued": 0
        },
        {
          "mr": "6",
          "townland": "",
          "os": "",
          "sublocation_1": "",
          "sublocation_2": "",
          "occupier": "Denis Noonan",
          "lessor": "Daniel Clanchy, Esq.",
          "desc": "H",
          "area": "",
          "land_val": "",
          "building_val": "1 0 0",
          "total_val": "1 0 0",
          "n_shared": 1,
          "is_total": 0,
          "is_exemption": 0,
          "is_continued": 0
        }
      ]
    }
  ]
}